subprocwriteread/README.MD
subprocwriteread/__init__.py
subprocwriteread/requirements.txt
subprocwriteread/thirdparty.json
subprocwriteread-0.12.dist-info/LICENSE.rst
subprocwriteread-0.12.dist-info/METADATA
subprocwriteread-0.12.dist-info/WHEEL
subprocwriteread-0.12.dist-info/top_level.txt
subprocwriteread-0.12.dist-info/RECORD
