Metadata-Version: 2.1
Name: subprocwriteread
Version: 0.12
Summary: A class for interacting with subprocesses and capturing their input and output streams
Home-page: https://github.com/hansalemaos/subprocwriteread
Author: Johannes Fischer
Author-email: aulasparticularesdealemaosp@gmail.com
License: MIT
Keywords: subprocess,write
Classifier: Development Status :: 4 - Beta
Classifier: Programming Language :: Python :: 3 :: Only
Classifier: Programming Language :: Python :: 3.10
Classifier: Topic :: Software Development :: Libraries :: Python Modules
Classifier: Topic :: Utilities
License-File: LICENSE.rst
